
{
  "v": "5.6.6",
  "ip": 0,
  "op": 160,
  "fr": 60,
  "w": 1432,
  "h": 492,
  "layers": [
    {
      "ind": 1,
      "nm": "border_draw",
      "ty": 4,
      "ip": 0,
      "op": 160,
      "st": 0,
      "ks": {
        "o": { "k": 100 },
        "r": { "k": 0 },
        "p": { "k": [0, 0] },
        "a": { "k": [0, 0] },
        "s": { "k": [100, 100] }
      },
      "shapes": [
        {
          "ty": "gr",
          "it": [
            {
              "ty": "sh",
              "ks": {
                "k": {
                  "i": [
                    [0,0],
                    [0,0],
                    [0,0],
                    [0,0],
                    [0,0],
                    [0,0]
                  ],
                  "o": [
                    [0,0],
                    [0,0],
                    [0,0],
                    [0,0],
                    [0,0],
                    [0,0]
                  ],
                  "v": [
                    [164,2],
                    [2,2],
                    [2,490],
                    [1430,490],
                    [1430,2],
                    [1214,2]
                  ],
                  "c": false
                }
              }
            },
            {
              "ty": "st",
              "c": { "k": [0,0,0,1] },
              "w": { "k": 3 },
              "lc": 1,
              "lj": 1,
              "ml": 4,
              "o": { "k": 100 }
            },
            {
              "ty": "tm",
              "s": { "k": 0 },
              "e": {
                "a": 1,
                "k": [
                  {
                    "i": { "x": [0.27], "y": [1] },
                    "o": { "x": [0.5], "y": [0] },
                    "t": 0,
                    "s": [0]
                  },
                  {
                    "t": 66,
                    "s": [100]
                  }
                ]
              },
              "o": { "k": 0 },
              "m": 1
            }
          ]
        }
      ]
    }
  ],
  "assets": [],
}
